sidraconnector/__init__.py
sidraconnector/sdk/__init__.py
sidraconnector/sdk/constants.py
sidraconnector/sdk/utils.py
sidraconnector/sdk/api/__init__.py
sidraconnector/sdk/api/sidra/__init__.py
sidraconnector/sdk/api/sidra/core/__init__.py
sidraconnector/sdk/api/sidra/core/utils.py
sidraconnector/sdk/databricks/__init__.py
sidraconnector/sdk/databricks/datalake.py
sidraconnector/sdk/databricks/utils.py
sidraconnector/sdk/databricks/anomalydetection/__init__.py
sidraconnector/sdk/databricks/anomalydetection/anomalydetection.py
sidraconnector/sdk/databricks/datapreview/__init__.py
sidraconnector/sdk/databricks/datapreview/datapreviewservice.py
sidraconnector/sdk/databricks/dsuingestion/__init__.py
sidraconnector/sdk/databricks/dsuingestion/tabularingestion.py
sidraconnector/sdk/databricks/dsuingestion/tabularingestionservice.py
sidraconnector/sdk/databricks/dsuingestion/updatetables.py
sidraconnector/sdk/databricks/dsuingestion/models/__init__.py
sidraconnector/sdk/databricks/dsuingestion/models/fielddefinition.py
sidraconnector/sdk/databricks/piidetection/__init__.py
sidraconnector/sdk/databricks/piidetection/piidetection.py
sidraconnector/sdk/databricks/postprocessing/__init__.py
sidraconnector/sdk/databricks/postprocessing/tabularingestionpostprocessing.py
sidraconnector/sdk/databricks/reader/__init__.py
sidraconnector/sdk/databricks/reader/readerservice.py
sidraconnector/sdk/log/__init__.py
sidraconnector/sdk/log/logging.py
sidraconnector/sdk/log/notification.py
sidraconnector/sdk/metadata/__init__.py
sidraconnector/sdk/metadata/assetservice.py
sidraconnector/sdk/metadata/dataintakeprocessservice.py
sidraconnector/sdk/metadata/entityservice.py
sidraconnector/sdk/metadata/marservice.py
sidraconnector/sdk/metadata/providerservice.py
sidraconnector/sdk/metadata/models/__init__.py
sidraconnector/sdk/metadata/models/attributemodel.py
sidraconnector/sdk/metadata/models/builders.py
sidraconnector/sdk/metadata/models/dataintakeprocessmodel.py
sidraconnector-2025.8.1.post481.dist-info/LICENSE
sidraconnector-2025.8.1.post481.dist-info/METADATA
sidraconnector-2025.8.1.post481.dist-info/WHEEL
sidraconnector-2025.8.1.post481.dist-info/top_level.txt
sidraconnector-2025.8.1.post481.dist-info/RECORD
