Metadata-Version: 2.1
Name: sidraconnector
Version: 2025.8.1.post481
Summary: A SDK for Sidra connectors
Home-page: https://sidra.dev/
Author: Sidra Data Services
Author-email: info@sidra.dev
License: Copyright (C) Sidra Data Services - All Rights Reserved
License-File: LICENSE
